stdPython/__init__.py
stdPython/help.py
stdPython/information.py
stdPython-1.0.1.dist-info/LICENSE
stdPython-1.0.1.dist-info/METADATA
stdPython-1.0.1.dist-info/WHEEL
stdPython-1.0.1.dist-info/top_level.txt
stdPython-1.0.1.dist-info/RECORD
